Metadata-Version: 1.0
Name: naefdistributions
Version: 0.2
Summary: Gaussian and Binomial distributions
Home-page: UNKNOWN
Author: Rico Naef
Author-email: naefrico@gmail.com
License: UNKNOWN
Platform: UNKNOWN
